DualPerspective/__init__.py
DualPerspective/core.py
dualperspective-0.1.4.dist-info/METADATA
dualperspective-0.1.4.dist-info/WHEEL
dualperspective-0.1.4.dist-info/top_level.txt
dualperspective-0.1.4.dist-info/RECORD
