Metadata-Version: 2.4
Name: DualPerspective
Version: 0.1.4
Summary: Python interface for DualPerspective.jl - A Julia package for obtaining maximum-entropy solutions to underdetermined linear systems.
Author-email: "Michael P. Friedlander" <michael.friedlander@ubc.ca>
License-Expression: MIT
Project-URL: Homepage, https://github.com/MPF-Optimization-Laboratory/DualPerspective.jl
Project-URL: Bug Tracker, https://github.com/MPF-Optimization-Laboratory/DualPerspective.jl/issues
Classifier: Programming Language :: Python :: 3
Classifier: Operating System :: OS Independent
Requires-Python: >=3.7
Requires-Dist: juliacall>=0.9.7
Requires-Dist: numpy>=1.20.0
Requires-Dist: tomli>=2.0.0; python_version < "3.11"
Provides-Extra: test
Requires-Dist: pytest>=7.0.0; extra == "test"
